radiotray_ng_mpris/__init__.py
radiotray_ng_mpris/_version.py
radiotray_ng_mpris/cli.py
radiotray_ng_mpris/wrap.py
radiotray_ng_mpris-0.1.3.dist-info/LICENSE
radiotray_ng_mpris-0.1.3.dist-info/METADATA
radiotray_ng_mpris-0.1.3.dist-info/WHEEL
radiotray_ng_mpris-0.1.3.dist-info/entry_points.txt
radiotray_ng_mpris-0.1.3.dist-info/top_level.txt
radiotray_ng_mpris-0.1.3.dist-info/RECORD
