Metadata-Version: 2.1
Name: radiotray-ng-mpris
Version: 0.1.3
Summary: A wrapper script for Radiotray-NG which provides an MPRIS2 interface.
Home-page: https://github.com/IngoMeyer441/radiotray-ng-mpris
Author: Ingo Meyer
Author-email: IJ_M@gmx.de
License: MIT
Keywords: multimedia
Classifier: Development Status :: 5 - Production/Stable
Classifier: Intended Audience :: End Users/Desktop
Classifier: License :: OSI Approved :: MIT License
Classifier: Natural Language :: English
Classifier: Operating System :: POSIX :: Linux
Classifier: Programming Language :: Python
Classifier: Programming Language :: Python :: 3
Classifier: Programming Language :: Python :: 3 :: Only
Classifier: Programming Language :: Python :: 3.10
Classifier: Programming Language :: Python :: 3.11
Classifier: Programming Language :: Python :: 3.12
Classifier: Topic :: Multimedia :: Sound/Audio :: Players
Requires-Python: ~=3.10
License-File: LICENSE
Requires-Dist: mpris-server
Requires-Dist: pydbus
Requires-Dist: yacl
